{"question":"\r\n<div class='specificatio'>\r\n<p class=\"p1\">The followig diagam shows the gaph of a fuctio \\(f\\).<p>\r\n<p class=\"p1\" style=\"text-alig: cete;\"><img sc=\".ib-questiobak-attachmets.s3.amazoaws.comuploadstiymce_assetasset1301Schemafbeeldig_2016-01-13_om_05.56.49.pg\" alt=\"\" ><p>\r\n<div>\r\n\r\n<div class='questio' style='paddig-left: 20px; paddig-ight: 20px;'>\r\n<p class=\"p1\">Fid \\({f^{ - 1}}( - 1)\\).<p>\r\n<div class='maks'>[2]<div>\r\n<div class='questio_pat_label'>a.<div>\r\n<div>\r\n<div class='questio' style='paddig-left: 20px; paddig-ight: 20px;'>\r\n<p class=\"p1\">Fid \\((f \\cic f)( - 1)\\).<p>\r\n<div class='maks'>[3]<div>\r\n<div class='questio_pat_label'>b.<div>\r\n<div>\r\n<div class='questio' style='paddig-left: 20px; paddig-ight: 20px;'>\r\n<p class=\"p1\">O the same diagam, sketch the gaph of \\(y = f( - x)\\).<p>\r\n<div class='maks'>[2]<div>\r\n<div class='questio_pat_label'>c.<div>\r\n<div>\r\n","markschems":"\r\n<div class='question' style='padding-left: 20px;'>\r\n<p>valid approach &nbsp; &nbsp; <strong><em>(M1)</em></strong></p>\r\n<p><em>eg</em>\\(\\;\\;\\;\\)horizontal line on graph at \\( - 1,{\\text{ }}f(a) =&nbsp; - 1,{\\text{ }}( - 1,5)\\)</p>\r\n<p>\\({f^{ - 1}}( - 1) = 5\\) &nbsp; &nbsp; <strong><em>A1 &nbsp; &nbsp; N2</em></strong></p>\r\n<p><strong><em>[2 marks]</em></strong></p>\r\n<div class='question_part_label'>a.</div>\r\n</div>\r\n<div class='question' style='padding-left: 20px;'>\r\n<p class=\"p1\">attempt to find \\(f( - 1)\\) <span class=\"Apple-converted-space\">&nbsp; &nbsp; </span><strong><em>(M1)</em></strong></p>\r\n<p class=\"p1\"><em>eg</em>\\(\\;\\;\\;\\)line on graph</p>\r\n<p class=\"p1\">\\(f( - 1) = 2\\) <span class=\"Apple-converted-space\">&nbsp; &nbsp; </span><strong><em>(A1)</em></strong></p>\r\n<p class=\"p1\">\\((f \\circ f)( - 1) = 1\\) <span class=\"Apple-converted-space\">&nbsp; &nbsp; </span><strong><em>A1 <span class=\"Apple-converted-space\">&nbsp; &nbsp; </span>N3</em></strong></p>\r\n<p class=\"p1\"><strong><em>[3 marks]</em></strong></p>\r\n<div class='question_part_label'>b.</div>\r\n</div>\r\n<div class='question' style='padding-left: 20px;'>\r\n<p class=\"p1\"><span class=\"s1\"><img src=\"./ib-questionbank-attachments.s3.amazonaws.com/uploads/tinymce_asset/asset/1302/Schermafbeelding_2016-01-13_om_06.13.13.png\" alt=\"\" />&nbsp;<span class=\"Apple-converted-space\">&nbsp; &nbsp; </span></span><strong><em>A1A1 <span class=\"Apple-converted-space\">&nbsp; &nbsp; </span>N2</em></strong></p>\r\n<p class=\"p2\">&nbsp;</p>\r\n<p class=\"p1\"><strong>Note: <span class=\"Apple-converted-space\">&nbsp; &nbsp; </span></strong>The shape <strong>must </strong>be an approximately correct shape (concave down and increasing). <strong>Only </strong>if the shape is approximately correct, award the following for points in circles:</p>\r\n<p class=\"p1\"><strong><em>A1 </em></strong>for the \\(y\\)-intercept,</p>\r\n<p class=\"p1\"><strong><em>A1 </em></strong>for any <strong>two </strong>of these points \\(( - 5,{\\text{ }} - 1),{\\text{ }}( - 2,{\\text{ }}1),{\\text{ }}(1,{\\text{ }}2)\\).</p>\r\n<p class=\"p1\"><em><strong>[2 marks]</strong></em></p>\r\n<p class=\"p1\"><em><strong>Total [7 marks]</strong></em></p>\r\n<div class='question_part_label'>c.</div>\r\n</div>\r\n","topic0":"Topic 2 - Functions and equations","topic1":"2.3","topic2":"Transformations of graphs.","ReferenceCode":"15M.1.sl.TZ1.4"}