{"question":"\r\n<div class='specificatio'>\r\n<p>The adom vaiable \\(X\\) is omally distibuted with a mea of 100. The followig diagam shows the omal cuve fo \\(X\\).<p>\r\n<p style=\"text-alig: cete;\"><img sc=\".ib-questiobak-attachmets.s3.amazoaws.comuploadstiymce_assetasset3534Schemafbeeldig_2017-08-11_om_16.32.27.pg\" alt=\"M175MATMESP1ENGTZ203\" ><p>\r\n<p>Let \\(R\\) be the shaded egio ude the cuve, to the ight of 107. The aea of \\(R\\) is 0.24.<p>\r\n<div>\r\n\r\n<div class='questio' style='paddig-left: 20px; paddig-ight: 20px;'>\r\n<p>Wite dow \\({\\text{P}}(X &gt; 107)\\).<p>\r\n<div class='maks'>[1]<div>\r\n<div class='questio_pat_label'>a.<div>\r\n<div>\r\n<div class='questio' style='paddig-left: 20px; paddig-ight: 20px;'>\r\n<p>Fid \\({\\text{P}}(100 &lt; X &lt; 107)\\).<p>\r\n<div class='maks'>[3]<div>\r\n<div class='questio_pat_label'>b.<div>\r\n<div>\r\n<div class='questio' style='paddig-left: 20px; paddig-ight: 20px;'>\r\n<p>Fid \\({\\text{P}}(93 &lt; X &lt; 107)\\).<p>\r\n<div class='maks'>[2]<div>\r\n<div class='questio_pat_label'>c.<div>\r\n<div>\r\n","markschems":"\r\n<div class='question' style='padding-left: 20px;'>\r\n<p>\\({\\text{P}}(X &gt; 107) = 0.24\\,\\,\\,\\left( { = \\frac{6}{{25}},{\\text{ }}24\\% } \\right)\\) &nbsp; &nbsp; <strong><em>A1</em></strong> &nbsp; &nbsp; <strong><em>N1</em></strong></p>\r\n<p><strong><em>[1 mark]</em></strong></p>\r\n<div class='question_part_label'>a.</div>\r\n</div>\r\n<div class='question' style='padding-left: 20px;'>\r\n<p>valid approach &nbsp; &nbsp; <strong><em>(M1)</em></strong></p>\r\n<p><em>eg</em>\\(\\,\\,\\,\\,\\,\\)\\({\\text{P}}(X &gt; 100) = 0.5,{\\text{ P}}(X &gt; 100) - {\\text{P}}(X &gt; 107)\\)</p>\r\n<p>correct working &nbsp; &nbsp; <strong><em>(A1)</em></strong></p>\r\n<p><em>eg</em>\\(\\,\\,\\,\\,\\,\\)\\(0.5 - 0.24,{\\text{ }}0.76 - 0.5\\)</p>\r\n<p>\\({\\text{P}}(100 &lt; X &lt; 107) = 0.26\\,\\,\\,\\left( { = \\frac{{13}}{{50}},{\\text{ }}26\\% } \\right)\\) &nbsp; &nbsp; <strong><em>A1</em></strong> &nbsp; &nbsp; <strong><em>N2</em></strong></p>\r\n<p><strong><em>[3 marks]</em></strong></p>\r\n<div class='question_part_label'>b.</div>\r\n</div>\r\n<div class='question' style='padding-left: 20px;'>\r\n<p>valid approach &nbsp; &nbsp; <strong><em>(M1)</em></strong></p>\r\n<p><em>eg</em>\\(\\,\\,\\,\\,\\,\\)\\(2 \\times 0.26,{\\text{ }}1 - 2(0.24),{\\text{ P}}(93 &lt; X &lt; 100) = {\\text{P}}(100 &lt; X &lt; 107)\\)</p>\r\n<p>\\({\\text{P}}(93 &lt; X &lt; 107) = 0.52\\,\\,\\,\\left( { = \\frac{{13}}{{25}},{\\text{ }}52\\% } \\right)\\) &nbsp; &nbsp; <strong><em>A1 N2</em></strong></p>\r\n<p><strong><em>[2 marks]</em></strong></p>\r\n<div class='question_part_label'>c.</div>\r\n</div>\r\n","topic0":"Topic 5 - Statistics and probability","topic1":"5.9","topic2":"\r\n","ReferenceCode":"17M.1.sl.TZ2.3"}